soccer_sdk_utils/__init__.py
soccer_sdk_utils/anchor.py
soccer_sdk_utils/division.py
soccer_sdk_utils/gender.py
soccer_sdk_utils/page.py
soccer_sdk_utils/tools.py
soccer_sdk_utils/dao/__init__.py
soccer_sdk_utils/dao/base.py
soccer_sdk_utils/dao/bltoken.py
soccer_sdk_utils/dao/city.py
soccer_sdk_utils/dao/club.py
soccer_sdk_utils/dao/club_translation.py
soccer_sdk_utils/dao/conference.py
soccer_sdk_utils/dao/country.py
soccer_sdk_utils/dao/image.py
soccer_sdk_utils/dao/match.py
soccer_sdk_utils/dao/organization.py
soccer_sdk_utils/dao/player.py
soccer_sdk_utils/dao/school.py
soccer_sdk_utils/dao/state_province.py
soccer_sdk_utils/dao/suggestion.py
soccer_sdk_utils/dao/user.py
soccer_sdk_utils/model/__init__.py
soccer_sdk_utils/model/bltoken.py
soccer_sdk_utils/model/city.py
soccer_sdk_utils/model/club.py
soccer_sdk_utils/model/club_translation.py
soccer_sdk_utils/model/coach.py
soccer_sdk_utils/model/commitment.py
soccer_sdk_utils/model/conference.py
soccer_sdk_utils/model/country.py
soccer_sdk_utils/model/image.py
soccer_sdk_utils/model/images.py
soccer_sdk_utils/model/league.py
soccer_sdk_utils/model/match.py
soccer_sdk_utils/model/meta.py
soccer_sdk_utils/model/ncaa.py
soccer_sdk_utils/model/player.py
soccer_sdk_utils/model/school.py
soccer_sdk_utils/model/state_province.py
soccer_sdk_utils/model/suggestion.py
soccer_sdk_utils/model/team.py
soccer_sdk_utils/model/tgs.py
soccer_sdk_utils/model/transfer.py
soccer_sdk_utils/model/user.py
soccer_sdk_utils/model/values.py
soccer_sdk_utils/schema/__init__.py
soccer_sdk_utils/schema/bltoken.py
soccer_sdk_utils/schema/city.py
soccer_sdk_utils/schema/club.py
soccer_sdk_utils/schema/club_translation.py
soccer_sdk_utils/schema/coach.py
soccer_sdk_utils/schema/commitment.py
soccer_sdk_utils/schema/conference.py
soccer_sdk_utils/schema/country.py
soccer_sdk_utils/schema/image.py
soccer_sdk_utils/schema/images.py
soccer_sdk_utils/schema/league.py
soccer_sdk_utils/schema/match.py
soccer_sdk_utils/schema/meta.py
soccer_sdk_utils-0.1.14.dist-info/LICENSE
soccer_sdk_utils-0.1.14.dist-info/METADATA
soccer_sdk_utils-0.1.14.dist-info/WHEEL
soccer_sdk_utils-0.1.14.dist-info/top_level.txt
soccer_sdk_utils-0.1.14.dist-info/RECORD
