Metadata-Version: 2.1
Name: soccer-sdk-utils
Version: 0.1.14
Summary: A python module housing Soccer SDK utilities
Author-email: Omar Crosby <omar.crosby@gmail.com>
Project-URL: Homepage, https://github.com/ocrosby/soccer-sdk-utils
Project-URL: Bug Tracker, https://github.com/ocrosby/soccer-sdk-utils/issues
Keywords: soccer,scraping
Classifier: Programming Language :: Python :: 3
Classifier: License :: OSI Approved :: GNU General Public License (GPL)
Classifier: Operating System :: OS Independent
Requires-Python: >=3.10
License-File: LICENSE
Requires-Dist: azure-cosmos (==4.3.0)
Requires-Dist: azure-core (==1.25.1)
Requires-Dist: beautifulsoup4 (==4.11.1)
Requires-Dist: flask (==2.2.2)
Requires-Dist: flask-bcrypt (==1.0.1)
Requires-Dist: marshmallow (==3.18.0)
Requires-Dist: python-dotenv (==0.21.0)
Requires-Dist: requests (==2.28.1)
